[{"solar": 370.92, "year": 2014, "month": "March", "trigen": 5327.4, "sce": 328.54},{"solar": 5645.61, "year": 2014, "month": "April", "trigen": 95442.71, "sce": 21437.18},{"solar": 6026.77, "year": 2014, "month": "May", "trigen": 87850.37, "sce": 27155.91},{"solar": 6998.67, "year": 2014, "month": "June", "trigen": 90902.71, "sce": 13345.64},{"solar": 5493.32, "year": 2014, "month": "July", "trigen": 94846.73, "sce": 27308.4},{"solar": 6414.88, "year": 2014, "month": "August", "trigen": 94419.25, "sce": 25132.23},{"solar": 5252.43, "year": 2014, "month": "September", "trigen": 86307.96, "sce": 50441.02},{"solar": 4125.13, "year": 2014, "month": "October", "trigen": 94690.22, "sce": 32248.2},{"solar": 3744.51, "year": 2014, "month": "November", "trigen": 85629.58, "sce": 21231.59},{"solar": 2817.93, "year": 2014, "month": "December", "trigen": 40113.08, "sce": 61637.0},{"solar": 3387.98, "year": 2015, "month": "January", "trigen": 80232.09, "sce": 21320.07},{"solar": 4407.39, "year": 2015, "month": "February", "trigen": 87488.99, "sce": 27393.65},{"solar": 5277.63, "year": 2015, "month": "March", "trigen": 96233.48, "sce": 23647.83},{"solar": 5557.56, "year": 2015, "month": "April", "trigen": 90766.91, "sce": 25369.0},{"solar": 4912.06, "year": 2015, "month": "May", "trigen": 85113.2, "sce": 20919.26},{"solar": 5987.23, "year": 2015, "month": "June", "trigen": 90787.51, "sce": 23334.32},{"solar": 5234.11, "year": 2015, "month": "July", "trigen": 88218.33, "sce": 33182.63},{"solar": 4233.04, "year": 2015, "month": "August", "trigen": 90832.3, "sce": 44757.61},{"solar": 3658.31, "year": 2015, "month": "September", "trigen": 94688.19, "sce": 58147.12},{"solar": 2973.88, "year": 2015, "month": "October", "trigen": 94752.49, "sce": 48235.6},{"solar": 2753.33, "year": 2015, "month": "November", "trigen": 82177.07, "sce": 27702.97},{"solar": 2305.83, "year": 2015, "month": "December", "trigen": 86104.67, "sce": 12983.32},{"solar": 2597.19, "year": 2016, "month": "January", "trigen": 80171.33, "sce": 15753.33},{"solar": 4845.36, "year": 2016, "month": "February", "trigen": 89313.04, "sce": 27550.06},{"solar": 4787.58, "year": 2016, "month": "March", "trigen": 80075.16, "sce": 19673.17}]
